aliyunsdkobjectdet/__init__.py
aliyunsdkobjectdet/endpoint.py
aliyunsdkobjectdet/request/__init__.py
aliyunsdkobjectdet/request/v20191230/ClassifyVehicleInsuranceRequest.py
aliyunsdkobjectdet/request/v20191230/DetectIPCObjectRequest.py
aliyunsdkobjectdet/request/v20191230/DetectKitchenAnimalsRequest.py
aliyunsdkobjectdet/request/v20191230/DetectMainBodyRequest.py
aliyunsdkobjectdet/request/v20191230/DetectObjectRequest.py
aliyunsdkobjectdet/request/v20191230/DetectTransparentImageRequest.py
aliyunsdkobjectdet/request/v20191230/DetectVehicleICongestionRequest.py
aliyunsdkobjectdet/request/v20191230/DetectVehicleIllegalParkingRequest.py
aliyunsdkobjectdet/request/v20191230/DetectVehicleRequest.py
aliyunsdkobjectdet/request/v20191230/DetectVideoIPCObjectRequest.py
aliyunsdkobjectdet/request/v20191230/DetectWhiteBaseImageRequest.py
aliyunsdkobjectdet/request/v20191230/DetectWorkwearRequest.py
aliyunsdkobjectdet/request/v20191230/GetAsyncJobResultRequest.py
aliyunsdkobjectdet/request/v20191230/RecognizeVehicleDamageRequest.py
aliyunsdkobjectdet/request/v20191230/RecognizeVehicleDashboardRequest.py
aliyunsdkobjectdet/request/v20191230/RecognizeVehiclePartsRequest.py
aliyunsdkobjectdet/request/v20191230/__init__.py
aliyun_python_sdk_objectdet-1.0.16.dist-info/LICENSE
aliyun_python_sdk_objectdet-1.0.16.dist-info/METADATA
aliyun_python_sdk_objectdet-1.0.16.dist-info/WHEEL
aliyun_python_sdk_objectdet-1.0.16.dist-info/top_level.txt
aliyun_python_sdk_objectdet-1.0.16.dist-info/RECORD
